{
    "statusCode": 0,
    "message": "success",
    "data": {
        "list": [
            {
                "id": 9583738,
                "jgid": 3863,
                "uid": 2352799,
                "group_id": 600,
                "cardtype": 1,
                "card_name": "年卡",
                "cardid": 369445,
                "cardno": "379246419n",
                "activedjgid": 3863,
                "lend_time": null,
                "return_time": null,
                "stopcard_start_time": null,
                "remarks": null,
                "stopcard_end_time": null,
                "endtime": "2021-04-20",
                "childId": 2352799,
                "renewal_type": 0,
                "begintime": "2020-04-20",
                "update_time": "0000-00-00 00:00:00",
                "child_name": "国防",
                "age": "0.7",
                "birthday": "2019-12-20",
                "gender": 1,
                "relationship": 502,
                "mobile": "13167358875",
                "nickname": "国防",
                "faceimg": "https:\/\/scdn.yourbay.net\/tst\/ui\/my\/logo.jpeg",
                "title": "北京悠贝朝阳未来广场双语馆"
            },
            {
                "id": 9569566,
                "jgid": 3863,
                "uid": 2064467,
                "group_id": 600,
                "cardtype": 1,
                "card_name": "年卡",
                "cardid": 364763,
                "cardno": "747217696y",
                "activedjgid": 3863,
                "lend_time": "2020-01-18 15:36:32",
                "return_time": "2020-07-07 11:40:45",
                "stopcard_start_time": null,
                "remarks": null,
                "stopcard_end_time": null,
                "endtime": "2021-01-18",
                "childId": 2064467,
                "renewal_type": 0,
                "begintime": "2020-01-18",
                "update_time": "0000-00-00 00:00:00",
                "child_name": "李若溪",
                "age": "3.5",
                "birthday": "2017-04-01",
                "gender": 1,
                "relationship": 502,
                "mobile": "13520013521",
                "nickname": "李若溪",
                "faceimg": "https:\/\/scdn.yourbay.net\/tst\/ui\/my\/logo.jpeg",
                "title": "北京悠贝朝阳未来广场双语馆"
            },
            {
                "id": 9561642,
                "jgid": 3863,
                "uid": 2043336,
                "group_id": 600,
                "cardtype": 3,
                "card_name": "月卡",
                "cardid": 362694,
                "cardno": "537122732z",
                "activedjgid": 3863,
                "lend_time": "2020-01-19 18:22:56",
                "return_time": "2020-06-21 15:19:24",
                "stopcard_start_time": null,
                "remarks": null,
                "stopcard_end_time": null,
                "endtime": "2020-06-21",
                "childId": 2043336,
                "renewal_type": 0,
                "begintime": "2020-01-11",
                "update_time": "0000-00-00 00:00:00",
                "child_name": "颜孟彤",
                "age": "1.7",
                "birthday": "2018-12-15",
                "gender": 2,
                "relationship": 503,
                "mobile": "13611096188",
                "nickname": "颜孟彤",
                "faceimg": "https:\/\/scdn.yourbay.net\/tst\/ui\/my\/logo.jpeg",
                "title": "北京悠贝朝阳未来广场双语馆"
            },
            {
                "id": 9520947,
                "jgid": 3863,
                "uid": 1925813,
                "group_id": 600,
                "cardtype": 1,
                "card_name": "年卡",
                "cardid": 350285,
                "cardno": "809307803b",
                "activedjgid": 3863,
                "lend_time": "2020-09-10 18:29:00",
                "return_time": "2020-05-16 15:30:33",
                "stopcard_start_time": null,
                "remarks": null,
                "stopcard_end_time": null,
                "endtime": "2020-12-13",
                "childId": 1925813,
                "renewal_type": 0,
                "begintime": "2019-12-13",
                "update_time": "0000-00-00 00:00:00",
                "child_name": "师铭悦",
                "age": "2.2",
                "birthday": "2018-07-11",
                "gender": 2,
                "relationship": 503,
                "mobile": "13552748565",
                "nickname": "师铭悦",
                "faceimg": "https:\/\/scdn.yourbay.net\/tst\/ui\/my\/logo.jpeg",
                "title": "北京悠贝朝阳未来广场双语馆"
            },
            {
                "id": 9502370,
                "jgid": 3863,
                "uid": 1863350,
                "group_id": 600,
                "cardtype": 1,
                "card_name": "年卡",
                "cardid": 344572,
                "cardno": "242631509f",
                "activedjgid": 3863,
                "lend_time": "2020-08-09 12:46:56",
                "return_time": "2020-08-11 18:51:20",
                "stopcard_start_time": null,
                "remarks": null,
                "stopcard_end_time": null,
                "endtime": "2020-12-01",
                "childId": 1863350,
                "renewal_type": 0,
                "begintime": "2019-12-01",
                "update_time": "0000-00-00 00:00:00",
                "child_name": "王禹兮",
                "age": "3.4",
                "birthday": "2017-05-04",
                "gender": 2,
                "relationship": 503,
                "mobile": "18622490595",
                "nickname": "张曦元",
                "faceimg": "https:\/\/scdn.yourbay.net\/tst\/ui\/my\/logo.jpeg",
                "title": "北京悠贝朝阳未来广场双语馆"
            },
            {
                "id": 9472740,
                "jgid": 3863,
                "uid": 1789522,
                "group_id": 600,
                "cardtype": 1,
                "card_name": "年卡",
                "cardid": 334358,
                "cardno": "105735216g",
                "activedjgid": 3863,
                "lend_time": "2020-05-09 16:36:05",
                "return_time": "2020-05-09 16:35:51",
                "stopcard_start_time": null,
                "remarks": null,
                "stopcard_end_time": null,
                "endtime": "2020-11-16",
                "childId": 1789522,
                "renewal_type": 0,
                "begintime": "2019-11-16",
                "update_time": "0000-00-00 00:00:00",
                "child_name": "刘一丁（李莫）",
                "age": "4.2",
                "birthday": "2016-07-13",
                "gender": 1,
                "relationship": 503,
                "mobile": "13720095167",
                "nickname": "李莫",
                "faceimg": "https:\/\/scdn.yourbay.net\/tst\/ui\/my\/logo.jpeg",
                "title": "北京悠贝朝阳未来广场双语馆"
            },
            {
                "id": 9472100,
                "jgid": 3863,
                "uid": 1788308,
                "group_id": 600,
                "cardtype": 3,
                "card_name": "月卡",
                "cardid": 334111,
                "cardno": "394673163d",
                "activedjgid": 3863,
                "lend_time": "2020-01-05 11:17:38",
                "return_time": "2020-01-11 10:40:49",
                "stopcard_start_time": null,
                "remarks": null,
                "stopcard_end_time": null,
                "endtime": "2020-01-16",
                "childId": 1788308,
                "renewal_type": 0,
                "begintime": "2019-11-16",
                "update_time": "0000-00-00 00:00:00",
                "child_name": "杨新怡",
                "age": "2.9",
                "birthday": "2017-10-20",
                "gender": 2,
                "relationship": 504,
                "mobile": "13853439666",
                "nickname": "杨新怡",
                "faceimg": "https:\/\/scdn.yourbay.net\/tst\/ui\/my\/logo.jpeg",
                "title": "北京悠贝朝阳未来广场双语馆"
            },
            {
                "id": 9472848,
                "jgid": 3863,
                "uid": 1789691,
                "group_id": 600,
                "cardtype": 3,
                "card_name": "月卡",
                "cardid": 334403,
                "cardno": "969788658p",
                "activedjgid": 3863,
                "lend_time": "2019-11-16 16:41:14",
                "return_time": "2019-12-14 16:38:10",
                "stopcard_start_time": null,
                "remarks": null,
                "stopcard_end_time": null,
                "endtime": "2019-12-16",
                "childId": 1789691,
                "renewal_type": 0,
                "begintime": "2019-11-16",
                "update_time": "0000-00-00 00:00:00",
                "child_name": "田宏宇",
                "age": "3.4",
                "birthday": "2017-04-14",
                "gender": 1,
                "relationship": 503,
                "mobile": "13693551725",
                "nickname": "田宏宇",
                "faceimg": "https:\/\/scdn.yourbay.net\/tst\/ui\/my\/logo.jpeg",
                "title": "北京悠贝朝阳未来广场双语馆"
            },
            {
                "id": 9468969,
                "jgid": 3863,
                "uid": 1780085,
                "group_id": 600,
                "cardtype": 3,
                "card_name": "月卡",
                "cardid": 333126,
                "cardno": "253120886h",
                "activedjgid": 3863,
                "lend_time": "2020-01-18 13:18:36",
                "return_time": "2020-04-19 16:00:51",
                "stopcard_start_time": null,
                "remarks": null,
                "stopcard_end_time": null,
                "endtime": "2020-02-14",
                "childId": 1780085,
                "renewal_type": 0,
                "begintime": "2019-11-14",
                "update_time": "0000-00-00 00:00:00",
                "child_name": "刘小漾",
                "age": "2.5",
                "birthday": "2018-03-16",
                "gender": 2,
                "relationship": 503,
                "mobile": "18911442501",
                "nickname": "那仁",
                "faceimg": "https:\/\/scdn.yourbay.net\/tst\/ui\/my\/logo.jpeg",
                "title": "北京悠贝朝阳未来广场双语馆"
            },
            {
                "id": 9454791,
                "jgid": 3863,
                "uid": 1738387,
                "group_id": 600,
                "cardtype": 1,
                "card_name": "年卡",
                "cardid": 328242,
                "cardno": "569414342y",
                "activedjgid": 3863,
                "lend_time": "2020-08-11 18:12:06",
                "return_time": "2020-08-11 18:46:14",
                "stopcard_start_time": null,
                "remarks": null,
                "stopcard_end_time": null,
                "endtime": "2020-11-07",
                "childId": 1738387,
                "renewal_type": 0,
                "begintime": "2019-11-07",
                "update_time": "0000-00-00 00:00:00",
                "child_name": "李佳倪",
                "age": "3.5",
                "birthday": "2017-03-17",
                "gender": 2,
                "relationship": 503,
                "mobile": "13520393999",
                "nickname": "李家倪",
                "faceimg": "https:\/\/scdn.yourbay.net\/tst\/ui\/my\/logo.jpeg",
                "title": "北京悠贝朝阳未来广场双语馆"
            }
        ],
        "listTotal": 71
    }
}